ai_robot_position_scraper-0.0.6.dist-info/licenses/LICENSE
position_scraper/__init__.py
position_scraper/position_scraper.py
ai_robot_position_scraper-0.0.6.dist-info/METADATA
ai_robot_position_scraper-0.0.6.dist-info/WHEEL
ai_robot_position_scraper-0.0.6.dist-info/top_level.txt
ai_robot_position_scraper-0.0.6.dist-info/RECORD
