Metadata-Version: 2.4
Name: ai_robot_position_scraper
Version: 0.0.6
Summary: Position scraper library for AI-Robot
Home-page: https://github.com/aruncs31s/ai_robot_position_scraper
Author: Arun CS
Author-email: your.email@example.com
License-File: LICENSE
Requires-Dist: requests
Dynamic: author
Dynamic: author-email
Dynamic: description
Dynamic: description-content-type
Dynamic: home-page
Dynamic: license-file
Dynamic: requires-dist
Dynamic: summary
